{
  "enabled": true,
  "neededInstalledMods": [],
  "neededUninstalledMods": [],
  "spawns": [
    {
      "id": "exeggcute-1",
      "pokemon": "exeggcute",
      "type": "pokemon",
      "bucket": "common",
      "weight": 1.9,
      "level": "8-33",
      "spawnablePositionType": "grounded",
      "condition": {
        "neededBaseBlocks": [
          "#cobblemon:natural"
        ],
        "dimensions": [
          "minecraft:overworld"
        ],
        "minSkyLight": 8,
        "maxSkyLight": 15,
        "neededNearbyBlocks": [
          "#minecraft:jungle_logs",
          "minecraft:jungle_leaves",
          "minecraft:vine",
          "#minecraft:acacia_logs",
          "minecraft:acacia_leaves"
        ]
      }
    }
  ]
}