{
  "enabled": true,
  "neededInstalledMods": [],
  "neededUninstalledMods": [],
  "spawns": [
    {
      "id": "sandslash alolan-1",
      "pokemon": "sandslash alolan",
      "type": "pokemon",
      "bucket": "rare",
      "weight": 3,
      "level": "22-70",
      "spawnablePositionType": "grounded",
      "condition": {
        "neededBaseBlocks": [
          "#cobblemon:natural"
        ],
        "dimensions": [
          "minecraft:overworld"
        ],
        "neededNearbyBlocks": [
          "minecraft:ice",
          "minecraft:packed_ice",
          "minecraft:blue_ice",
          "minecraft:snow",
          "minecraft:snow_block"
        ]
      }
    }
  ]
}