{
  "target": "cobblemon:eiscue",
  "drops": {
    "amount": 7,
    "entries": [
      {
        "item": "minecraft:feather",
        "quantityRange": "0-1"
      },
      {
        "item": "minecraft:chicken"
      },
      {
        "item": "minecraft:cod",
        "quantityRange": "0-1"
      },
      {
        "item": "minecraft:blue_ice"
      },
      {
        "item": "cobblemon:aspear_berry",
        "percentage": 5
      },
      {
        "item": "mega_showdown:ice_tera_shard",
        "percentage": 10
      },
      {
        "item": "cobblemon:ice_gem",
        "percentage": 5
      }
    ]
  }
}