{
    "enabled": true,
    "neededInstalledMods": [],
    "neededUninstalledMods": [],
    "spawns": [
        {
            "id": "excadrill-1",
            "pokemon": "excadrill",
            "presets": [
                "base"
            ],
            "type": "pokemon",
            "spawnablePositionType": "grounded",
            "bucket": "common",
            "level": "31-51",
            "weight": 1.0,
            "condition": {
                "minSkyLight": 0,
                "maxSkyLight": 7,
                "biomes": [
                    "#cobblemon:is_overworld"
                ]
            },
            "anticondition": {
                "biomes": [
                    "#cobblemon:is_deep_dark"
                ]
            }
        }
    ]
}